odoo/addons/helpdesk_ticket_related/README.rst
odoo/addons/helpdesk_ticket_related/__init__.py
odoo/addons/helpdesk_ticket_related/__manifest__.py
odoo/addons/helpdesk_ticket_related/i18n/ca.po
odoo/addons/helpdesk_ticket_related/i18n/es.po
odoo/addons/helpdesk_ticket_related/i18n/helpdesk_ticket_related.pot
odoo/addons/helpdesk_ticket_related/i18n/it.po
odoo/addons/helpdesk_ticket_related/i18n/sv.po
odoo/addons/helpdesk_ticket_related/models/__init__.py
odoo/addons/helpdesk_ticket_related/models/helpdesk_ticket.py
odoo/addons/helpdesk_ticket_related/readme/CONTRIBUTORS.md
odoo/addons/helpdesk_ticket_related/readme/DESCRIPTION.md
odoo/addons/helpdesk_ticket_related/static/description/icon.png
odoo/addons/helpdesk_ticket_related/static/description/icon.svg
odoo/addons/helpdesk_ticket_related/static/description/index.html
odoo/addons/helpdesk_ticket_related/tests/__init__.py
odoo/addons/helpdesk_ticket_related/tests/test_related_tickets.py
odoo/addons/helpdesk_ticket_related/views/helpdesk_ticket_views.xml
odoo14_addon_helpdesk_ticket_related-14.0.1.0.1.dev1.dist-info/METADATA
odoo14_addon_helpdesk_ticket_related-14.0.1.0.1.dev1.dist-info/WHEEL
odoo14_addon_helpdesk_ticket_related-14.0.1.0.1.dev1.dist-info/top_level.txt
odoo14_addon_helpdesk_ticket_related-14.0.1.0.1.dev1.dist-info/RECORD
